multiweatherapi/__init__.py
multiweatherapi/campbell.py
multiweatherapi/davis.py
multiweatherapi/multiweatherapi.py
multiweatherapi/onset.py
multiweatherapi/rainwise.py
multiweatherapi/spectrum.py
multiweatherapi/utilities.py
multiweatherapi/zentra.py
multiweatherapi-0.0.25.dist-info/LICENSE
multiweatherapi-0.0.25.dist-info/METADATA
multiweatherapi-0.0.25.dist-info/WHEEL
multiweatherapi-0.0.25.dist-info/top_level.txt
multiweatherapi-0.0.25.dist-info/RECORD
