Metadata-Version: 2.1
Name: multiweatherapi
Version: 0.0.25
Summary: Python bindings to multiple weather station vendor APIs
Home-page: https://gitlab.msu.edu/adsdatascience/multiweatherapi
Author: Junhee Park
Author-email: jhp@msu.edu
License: UNKNOWN
Project-URL: Bug Tracker, https://gitlab.msu.edu/adsdatascience/multiweatherapi/-/issues
Platform: UNKNOWN
Classifier: Programming Language :: Python :: 3
Classifier: License :: OSI Approved :: MIT License
Classifier: Operating System :: OS Independent
Requires-Python: >=3.6
License-File: LICENSE
Requires-Dist: requests
Requires-Dist: pytz
